models/__init__.py
models/base.py
MongoSimplify-0.5.0.dist-info/LICENSE
MongoSimplify-0.5.0.dist-info/METADATA
MongoSimplify-0.5.0.dist-info/WHEEL
MongoSimplify-0.5.0.dist-info/top_level.txt
MongoSimplify-0.5.0.dist-info/RECORD
