Metadata-Version: 2.1
Name: MongoSimplify
Version: 0.5.0
Summary: MongoSimplify is a versatile Python library for easy and efficient MongoDB interaction.
Home-page: https://github.com/mukit-hasan/MongoSimplify
Author: Mukit Hasan
Author-email: mukithasan58@gmail.com
Keywords: python,pymongo,MongoSimplify,mongodb,nosql
Classifier: Programming Language :: Python :: 3
Classifier: License :: OSI Approved :: MIT License
Classifier: Operating System :: OS Independent
Requires-Python: >=3.11
License-File: LICENSE
Requires-Dist: pymongo
